README.md
setup.cfg
setup.py
predictivecontrol/__init__.py
predictivecontrol.egg-info/PKG-INFO
predictivecontrol.egg-info/SOURCES.txt
predictivecontrol.egg-info/dependency_links.txt
predictivecontrol.egg-info/not-zip-safe
predictivecontrol.egg-info/requires.txt
predictivecontrol.egg-info/top_level.txt