Metadata-Version: 1.0
Name: predictivecontrol
Version: 1.0
Summary: Python package which implements Predictive Control techniques (e.g., MPC, E-MPC)
Home-page: https://github.com/rgmaidana/predictiveControl
Author: Renan Maidana
Author-email: renan.maidana@acad.pucrs.br
License: MIT
Platform: UNKNOWN
